Metadata-Version: 2.4
Name: CodersanSamplePipProj
Version: 0.1
Summary: TYPE YOUR DESCRIPTION HERE
Home-page: https://github.com/user/ali7919
Download-URL: https://github.com/ali7919/CodersanSamplePipProj/archive/refs/tags/v0.1.tar.gz
Author: Ali Mobarekati
Author-email: ali7919mb@yhaoo.com
License: MIT
Keywords: SOME,MEANINGFULL,KEYWORDS
Classifier: Development Status :: 3 - Alpha
Classifier: Intended Audience :: Developers
Classifier: Topic :: Software Development :: Build Tools
Classifier: License :: OSI Approved :: MIT License
Classifier: Programming Language :: Python :: 3
Classifier: Programming Language :: Python :: 3.4
Classifier: Programming Language :: Python :: 3.5
Classifier: Programming Language :: Python :: 3.6
License-File: LICENSE.txt
Requires-Dist: numpy
Dynamic: author
Dynamic: author-email
Dynamic: classifier
Dynamic: download-url
Dynamic: home-page
Dynamic: keywords
Dynamic: license
Dynamic: license-file
Dynamic: requires-dist
Dynamic: summary
